oauth2helper/__init__.py
oauth2helper/_content.py
oauth2helper/_token.py
oauth2helper/starlette.py
oauth2helper/version.py
oauth2helper-3.4.0.dist-info/LICENSE
oauth2helper-3.4.0.dist-info/METADATA
oauth2helper-3.4.0.dist-info/WHEEL
oauth2helper-3.4.0.dist-info/top_level.txt
oauth2helper-3.4.0.dist-info/RECORD
