Metadata-Version: 2.1
Name: oauth2helper
Version: 3.4.0
Summary: Validate and extract information from OAuth2 token.
Home-page: https://colin-b.github.io/oauth2helper/
Author: Colin Bounouar
Author-email: colin.bounouar.dev@gmail.com
Maintainer: Colin Bounouar
Maintainer-email: colin.bounouar.dev@gmail.com
License: MIT
Download-URL: https://pypi.org/project/oauth2helper/
Project-URL: GitHub, https://github.com/Colin-b/oauth2helper
Project-URL: Changelog, https://github.com/Colin-b/oauth2helper/blob/master/CHANGELOG.md
Project-URL: Issues, https://github.com/Colin-b/oauth2helper/issues
Keywords: security,oauth2,jwt
Platform: Windows
Platform: Linux
Classifier: Development Status :: 5 - Production/Stable
Classifier: Intended Audience :: Developers
Classifier: License :: OSI Approved :: MIT License
Classifier: Natural Language :: English
Classifier: Programming Language :: Python
Classifier: Programming Language :: Python :: 3
Classifier: Programming Language :: Python :: 3.6
Classifier: Programming Language :: Python :: 3.7
Classifier: Programming Language :: Python :: 3.8
Classifier: Topic :: Software Development :: Build Tools
Requires-Python: >=3.6
Requires-Dist: requests (==2.*)
Requires-Dist: pyjwt (==1.*)
Requires-Dist: cryptography (==2.*)
Provides-Extra: testing
Requires-Dist: pytest-responses (==0.4.*) ; extra == 'testing'
Requires-Dist: pytest-cov (==2.*) ; extra == 'testing'
Requires-Dist: starlette (==0.13.*) ; extra == 'testing'
Requires-Dist: requests (==2.*) ; extra == 'testing'
